gethogs/__init__.py
gethogs/entity.py
gethogs/file_manager.py
gethogs/genome_merger.py
gethogs/lib.py
gethogs/settings.py
gethogs/statistic_tracker.py
gethogs/unionfind.py
gethogs-1.1.1.data/scripts/warthogs.py
gethogs-1.1.1.dist-info/LICENSE.txt
gethogs-1.1.1.dist-info/METADATA
gethogs-1.1.1.dist-info/WHEEL
gethogs-1.1.1.dist-info/top_level.txt
gethogs-1.1.1.dist-info/RECORD
