Metadata-Version: 2.1
Name: gethogs
Version: 1.1.1
Summary: A tool to infer Hierarchical Orthologous Groups (HOGs) from pairwise orthologs
Home-page: https://github.com/DessimozLab/gethogs
Author: Dessimoz Lab - Laboratory of Computational Evolutionary Biology and Genomics
Author-email: adrian.altenhoff@inf.ethz.ch
License: MIT
Keywords: orthology,HOGs,orthoxml,algorithm
Classifier: Development Status :: 4 - Beta
Classifier: Environment :: Console
Classifier: Intended Audience :: Developers
Classifier: Intended Audience :: Science/Research
Classifier: Topic :: Scientific/Engineering :: Bio-Informatics
Classifier: License :: OSI Approved :: MIT License
Classifier: Programming Language :: Python :: 2
Classifier: Programming Language :: Python :: 2.7
Classifier: Programming Language :: Python :: 3
Classifier: Programming Language :: Python :: 3.5
Classifier: Programming Language :: Python :: 3.6
Classifier: Programming Language :: Python :: 3.7
Classifier: Programming Language :: Python :: 3.8
Classifier: Programming Language :: Python :: 3.9
Classifier: Programming Language :: Python :: 3.10
Classifier: Programming Language :: Python :: 3.11
License-File: LICENSE.txt
Requires-Dist: lxml
Requires-Dist: numpy
Requires-Dist: biopython
